{
    "gears": 2,
    "springs": 2,
    "glowing": 1,
    "clarity": 10,
    "focused": 10,
    "\u00a7l\u00a70darkness": 1,
    "angelic": 5,
    "antitoxin": 10,
    "armored": 8,
    "band-aid": 1,
    "berserker": 3,
    "curse": 5,
    "deathbringer": 10,
    "deflect": 10,
    "diminish": 5,
    "cyberneticarmoured": 5,
    "cyberneticenlightened": 10,
    "drunk": 8,
    "endershift": 5,
    "enderwalker": 5,
    "enlighted": 5,
    "enlightened": 10,
    "etherealdodge": 10,
    "frozen": 5,
    "godlyoverload": 3,
    "heatwave": 4,
    "heavy": 10,
    "implants": 3,
    "metaphysical": 10,
    "molten": 10,
    "nourish": 10,
    "nurture": 5,
    "obscure": 10,
    "obsidianshield": 1,
    "overload": 3,
    "painkiller": 10,
    "revive": 5,
    "shockwave": 4,
    "tank": 10,
    "titantrap": 10,
    "valor": 8,
    "voodoo": 10,
    "accuracy": 5,
    "aerial": 5,
    "assassin": 5,
    "backstab": 5,
    "blessed": 3,
    "blind": 5,
    "block": 5,
    "charge": 5,
    "cripple": 5,
    "decapitation": 10,
    "demise": 5,
    "demonforged": 5,
    "demoniclifesteal": 2,
    "demonicsharpened": 3,
    "disarmor": 5,
    "disintegrate": 10,
    "dominate": 5,
    "doublestrike": 3,
    "execute": 10,
    "experiencehunter": 10,
    "freeze": 5,
    "frenzy": 10,
    "glory": 10,
    "gravity": 5,
    "hallucination": 5,
    "huntsman": 10,
    "iceaspect": 5,
    "incendiary": 3,
    "influx": 5,
    "insanity": 7,
    "inversion": 10,
    "lifesteal": 5,
    "lightning": 5,
    "maniac": 10,
    "poison": 5,
    "rage": 4,
    "sharpened": 5,
    "silence": 10,
    "soulsteal": 3,
    "ultrarage": 2,
    "wither": 5,
    "sergeonofdeath": 7,
    "overgrowth": 10,
    "bloodcurdle": 7,
    "alchemy": 3,
    "energycollector": 5,
    "jackpot": 10,
    "luck": 5,
    "meteorhunter": 5,
    "meteorsummoner": 5,
    "minerssight": 1,
    "oremagnet": 5,
    "oresurge": 10,
    "sharddiscoverer": 5,
    "shatter": 5,
    "superbreaker": 10,
    "transfuse": 3,
    "autorepair": 10
}